mpsym.libs/liblua5-0bfd16ed.2.so.0.0.0
mpsym/_mpsym_tests.py
mpsym/_mpsym.cpython-36m-x86_64-linux-gnu.so
mpsym/__init__.py
mpsym-0.6.2.dist-info/RECORD
mpsym-0.6.2.dist-info/METADATA
mpsym-0.6.2.dist-info/WHEEL
mpsym-0.6.2.dist-info/LICENSE.txt
mpsym-0.6.2.dist-info/top_level.txt
