Metadata-Version: 2.1
Name: mpsym
Version: 0.6.2
Summary: MPSoC Symmetry Reduction
Home-page: https://github.com/tud-ccc/mpsym
Author: Timo Nicolai
Author-email: timonicolai@arcor.de
License: MIT
Platform: UNKNOWN
